{
  "schemaVersion": 1,
  "owner": "OPL Console and OPL Fabric",
  "purpose": "Workspace persistent storage backup, restore-to-new-Workspace, and retention contract.",
  "state": "current",
  "machineBoundary": "VolumeSnapshot backup/restore behavior, retention deletion scope, API shape, and commercial billing rules.",
  "lifecycle": {
    "type": "long_term_contract",
    "removalCondition": "Replace only with a newer current contract for the same boundary."
  },
  "currentScope": "Workspace persistent storage backup, restore, and retention",
  "provider": "tencent-tke-volume-snapshot",
  "backupPolicy": {
    "defaultName": "daily_7_weekly_4",
    "retainDaily": 7,
    "retainWeekly": 4,
    "retainLast": 11,
    "restoreMode": "restore_to_new_workspace"
  },
  "resourceModel": {
    "source": "TKE PVC backed by Tencent CBS",
    "backup": "Kubernetes VolumeSnapshot",
    "restore": "new PVC using dataSource VolumeSnapshot",
    "deleteBackupDeletes": "VolumeSnapshot only",
    "deleteBackupNeverDeletes": [
      "source PVC",
      "restored PVC",
      "Workspace compute"
    ]
  },
  "api": {
    "createBackup": "POST /api/workspaces/storage-backups",
    "restoreBackup": "POST /api/workspaces/restore-storage-backup",
    "pruneBackups": "POST /api/workspaces/prune-storage-backups"
  },
  "ledgerReceipts": [
    "workspace.storage_backup_created",
    "workspace.storage_restored"
  ],
  "commercialRules": [
    "Restored Workspaces are new billable Workspaces.",
    "Restored Workspaces must freeze seven days of compute and storage before creation.",
    "Restored Workspaces charge the first hour immediately.",
    "Storage backup metadata must not contain Workspace access tokens."
  ],
  "nonGoals": [
    "in-place restore over an existing PVC",
    "cross-region disaster recovery",
    "application-level file versioning",
    "user-facing backup scheduler UI"
  ]
}
